tensorflow_privacy/__init__.py
tensorflow_privacy/version.py
tensorflow_privacy/privacy/__init__.py
tensorflow_privacy/privacy/analysis/__init__.py
tensorflow_privacy/privacy/analysis/compute_dp_sgd_privacy.py
tensorflow_privacy/privacy/analysis/compute_dp_sgd_privacy_lib.py
tensorflow_privacy/privacy/analysis/compute_dp_sgd_privacy_test.py
tensorflow_privacy/privacy/analysis/compute_noise_from_budget.py
tensorflow_privacy/privacy/analysis/compute_noise_from_budget_lib.py
tensorflow_privacy/privacy/analysis/compute_noise_from_budget_test.py
tensorflow_privacy/privacy/analysis/gdp_accountant.py
tensorflow_privacy/privacy/analysis/tensor_buffer.py
tensorflow_privacy/privacy/analysis/tensor_buffer_eager_test.py
tensorflow_privacy/privacy/analysis/tensor_buffer_graph_test.py
tensorflow_privacy/privacy/analysis/tree_aggregation_accountant.py
tensorflow_privacy/privacy/analysis/tree_aggregation_accountant_test.py
tensorflow_privacy/privacy/bolt_on/__init__.py
tensorflow_privacy/privacy/bolt_on/losses.py
tensorflow_privacy/privacy/bolt_on/losses_test.py
tensorflow_privacy/privacy/bolt_on/models.py
tensorflow_privacy/privacy/bolt_on/models_test.py
tensorflow_privacy/privacy/bolt_on/optimizers.py
tensorflow_privacy/privacy/bolt_on/optimizers_test.py
tensorflow_privacy/privacy/dp_query/__init__.py
tensorflow_privacy/privacy/dp_query/discrete_gaussian_query.py
tensorflow_privacy/privacy/dp_query/discrete_gaussian_query_test.py
tensorflow_privacy/privacy/dp_query/discrete_gaussian_utils.py
tensorflow_privacy/privacy/dp_query/discrete_gaussian_utils_test.py
tensorflow_privacy/privacy/dp_query/distributed_discrete_gaussian_query.py
tensorflow_privacy/privacy/dp_query/distributed_discrete_gaussian_query_test.py
tensorflow_privacy/privacy/dp_query/distributed_skellam_query.py
tensorflow_privacy/privacy/dp_query/distributed_skellam_query_test.py
tensorflow_privacy/privacy/dp_query/dp_query.py
tensorflow_privacy/privacy/dp_query/dp_query_test.py
tensorflow_privacy-0.8.12.dist-info/LICENSE
tensorflow_privacy-0.8.12.dist-info/METADATA
tensorflow_privacy-0.8.12.dist-info/WHEEL
tensorflow_privacy-0.8.12.dist-info/top_level.txt
tensorflow_privacy-0.8.12.dist-info/RECORD
